Metadata-Version: 1.0
Name: CIRCexplorer
Version: 1.1.10
Summary: A combined strategy to identify circular RNAs (circRNAs and ciRNAs)
Home-page: https://github.com/YangLab/CIRCexplorer
Author: Xu-Kai Ma
Author-email: maxukai@picb.ac.cn
License: MIT
Platform: UNKNOWN
